agility/__init__.py
agility/analysis.py
agility/minimiser.py
agility/plotting.py
agility-0.1.0.dist-info/licenses/LICENSE
agility-0.1.0.dist-info/METADATA
agility-0.1.0.dist-info/WHEEL
agility-0.1.0.dist-info/top_level.txt
agility-0.1.0.dist-info/RECORD
