Metadata-Version: 2.4
Name: agility
Version: 0.1.0
Summary: Analysis tool for simulations of grain boundaries and interfaces
Author-email: Alexander Bonkowski <alexander.bonkowski@rwth-aachen.de>
Maintainer: Alexander Bonkowski
License: MIT License
Project-URL: Repo, https://github.com/ab5424/agility
Project-URL: Package, https://pypi.org/project/agility/
Keywords: grain boundaries,interfaces,science,analysis
Classifier: Development Status :: 1 - Planning
Classifier: Intended Audience :: Science/Research
Classifier: License :: OSI Approved :: MIT License
Classifier: Operating System :: OS Independent
Classifier: Programming Language :: Python :: 3
Classifier: Programming Language :: Python :: 3.10
Classifier: Programming Language :: Python :: 3.11
Classifier: Programming Language :: Python :: 3.12
Classifier: Programming Language :: Python :: 3.13
Classifier: Topic :: Scientific/Engineering :: Physics
Classifier: Topic :: Scientific/Engineering :: Chemistry
Classifier: Topic :: Software Development :: Libraries :: Python Modules
Requires-Python: >=3.10
License-File: LICENSE
Requires-Dist: numpy>=1.25
Requires-Dist: pandas>=2
Requires-Dist: scipy>=1.12
Requires-Dist: seaborn>=0.13
Provides-Extra: strict
Requires-Dist: numpy==2.2.6; extra == "strict"
Requires-Dist: pandas==2.3.0; extra == "strict"
Requires-Dist: scipy==1.15.3; extra == "strict"
Requires-Dist: seaborn==0.13.2; extra == "strict"
Provides-Extra: tests
Requires-Dist: pytest-cov>=5; extra == "tests"
Requires-Dist: pytest-split>=0.9; extra == "tests"
Requires-Dist: pytest>=8; extra == "tests"
Provides-Extra: ovito
Requires-Dist: ovito>=3.8; extra == "ovito"
Provides-Extra: ase
Requires-Dist: ase>=3.23; extra == "ase"
Provides-Extra: pymatgen
Requires-Dist: pymatgen>=2024; extra == "pymatgen"
Dynamic: license-file
